setup.py
Jeev_Modules.egg-info/PKG-INFO
Jeev_Modules.egg-info/SOURCES.txt
Jeev_Modules.egg-info/dependency_links.txt
Jeev_Modules.egg-info/not-zip-safe
Jeev_Modules.egg-info/requires.txt
Jeev_Modules.egg-info/top_level.txt
jeev_modules.egg-info/SOURCES.txt
modules/__init__.py
modules/bitbucket.py
modules/catfacts.py
modules/coin.py
modules/dealwithit.py
modules/decide.py
modules/dinner.py
modules/eightball.py
modules/facts.py
modules/geocode.py
modules/hackernews.py
modules/haters.py
modules/jira.py
modules/kittens.py
modules/lol.py
modules/periodictest.py
modules/ping.py
modules/sed.py
modules/smile.py
modules/sudo.py
modules/tvrage.py
modules/webtest.py