Metadata-Version: 1.1
Name: jeev-modules
Version: 0.0.2
Summary: Modules for Jeev
Home-page: https://github.com/jhgg/jeev-modules
Author: Jacob Heinz
Author-email: me@jh.gg
License: MIT
Keywords: chat slack bot irc jeev
Platform: UNKNOWN
Classifier: Development Status :: 4 - Beta
Classifier: Topic :: Communications :: Chat
Classifier: Topic :: Utilities
Classifier: Framework :: Flask
Classifier: License :: OSI Approved :: MIT License
Classifier: Programming Language :: Python :: 2.7
Classifier: Programming Language :: Python :: 2 :: Only
Classifier: License :: OSI Approved :: MIT License
